gemeinsprache/__init__.py
gemeinsprache/posix.py
gemeinsprache/shell.py
gemeinsprache/time.py
gemeinsprache/utils.py
gemeinsprache-0.1.0.dist-info/LICENSE
gemeinsprache-0.1.0.dist-info/METADATA
gemeinsprache-0.1.0.dist-info/WHEEL
gemeinsprache-0.1.0.dist-info/top_level.txt
gemeinsprache-0.1.0.dist-info/RECORD
