Metadata-Version: 1.0
Name: gemeinsprache
Version: 0.1.0
Summary: General purpose utility functions and class objects required by other python projects
Home-page: https://github.com/ProbonoBonobo/gemeinsprache
Author: Kevin Zeidler
Author-email: kzeidler@gmail.com
License: COPYRIGHT 2019 Kevin Zeidler
